Workbook

Sheet Carga masiva
A2: Plantilla de carga masiva de gastos directos
A3: Complete una fila por gasto. No cambie los encabezados. Las columnas amarillas son editables.
A5: Registro | B5: Categoría código | C5: Centro de costo | D5: Partida | E5: Fecha | F5: Concepto | G5: Proveedor | H5: Descripción | I5: Monto | J5: Moneda factura | K5: Monto factura | L5: Tipo de cambio | M5: Fecha tipo cambio | N5: Factura(s) | O5: Estado de fila | P5: Observaciones de validación
A6: =IF(COUNTA(B6:N6)=0,"",ROW()-5) | O6: =IF(COUNTA(B6:N6)=0,"",IF(P6="","LISTO","REVISAR")) | P6: =IF(COUNTA(B6:N6)=0,"",TRIM(IF(B6="","Falta categoría. ","")&IF(AND(B6<>"",COUNTIF(Catalogos!$B$6:$B$12,B6)=0),"Categoría inválida. ","")&IF(C6="","Falta centro de costo. ","")&IF(D6="","Falta partida. ","")&IF(E6="","Falta fecha. ","")&IF(F6="","Falta concepto. ","")&IF(G6="","Falta proveedor. ","")&IF(I6="","Falta monto. ","")&IF(AND(I6<>"",I6<=0),"Monto inválido. ","")&IF(AND(COUNTA(J6:M6)>0,OR(J6="",K6="",L6="",M6="")),"Completa los 4 campos de moneda extranjera. ","")&IF(AND(J6<>"",COUNTIF(Catalogos!$F$6:$F$6,J6)=0),"Moneda de factura inválida. ","")&IF(AND(K6<>"",K6<=0),"Monto de factura inválido. ","")&IF(AND(L6<>"",L6<=0),"Tipo de cambio inválido. ","")))
A7: =IF(COUNTA(B7:N7)=0,"",ROW()-5) | O7: =IF(COUNTA(B7:N7)=0,"",IF(P7="","LISTO","REVISAR")) | P7: =IF(COUNTA(B7:N7)=0,"",TRIM(IF(B7="","Falta categoría. ","")&IF(AND(B7<>"",COUNTIF(Catalogos!$B$6:$B$12,B7)=0),"Categoría inválida. ","")&IF(C7="","Falta centro de costo. ","")&IF(D7="","Falta partida. ","")&IF(E7="","Falta fecha. ","")&IF(F7="","Falta concepto. ","")&IF(G7="","Falta proveedor. ","")&IF(I7="","Falta monto. ","")&IF(AND(I7<>"",I7<=0),"Monto inválido. ","")&IF(AND(COUNTA(J7:M7)>0,OR(J7="",K7="",L7="",M7="")),"Completa los 4 campos de moneda extranjera. ","")&IF(AND(J7<>"",COUNTIF(Catalogos!$F$6,J7)=0),"Moneda de factura inválida. ","")&IF(AND(K7<>"",K7<=0),"Monto de factura inválido. ","")&IF(AND(L7<>"",L7<=0),"Tipo de cambio inválido. ","")))
A8: =IF(COUNTA(B8:N8)=0,"",ROW()-5) | O8: =IF(COUNTA(B8:N8)=0,"",IF(P8="","LISTO","REVISAR")) | P8: =IF(COUNTA(B8:N8)=0,"",TRIM(IF(B8="","Falta categoría. ","")&IF(AND(B8<>"",COUNTIF(Catalogos!$B$6:$B$12,B8)=0),"Categoría inválida. ","")&IF(C8="","Falta centro de costo. ","")&IF(D8="","Falta partida. ","")&IF(E8="","Falta fecha. ","")&IF(F8="","Falta concepto. ","")&IF(G8="","Falta proveedor. ","")&IF(I8="","Falta monto. ","")&IF(AND(I8<>"",I8<=0),"Monto inválido. ","")&IF(AND(COUNTA(J8:M8)>0,OR(J8="",K8="",L8="",M8="")),"Completa los 4 campos de moneda extranjera. ","")&IF(AND(J8<>"",COUNTIF(Catalogos!$F$6,J8)=0),"Moneda de factura inválida. ","")&IF(AND(K8<>"",K8<=0),"Monto de factura inválido. ","")&IF(AND(L8<>"",L8<=0),"Tipo de cambio inválido. ","")))
A9: =IF(COUNTA(B9:N9)=0,"",ROW()-5) | O9: =IF(COUNTA(B9:N9)=0,"",IF(P9="","LISTO","REVISAR")) | P9: =IF(COUNTA(B9:N9)=0,"",TRIM(IF(B9="","Falta categoría. ","")&IF(AND(B9<>"",COUNTIF(Catalogos!$B$6:$B$12,B9)=0),"Categoría inválida. ","")&IF(C9="","Falta centro de costo. ","")&IF(D9="","Falta partida. ","")&IF(E9="","Falta fecha. ","")&IF(F9="","Falta concepto. ","")&IF(G9="","Falta proveedor. ","")&IF(I9="","Falta monto. ","")&IF(AND(I9<>"",I9<=0),"Monto inválido. ","")&IF(AND(COUNTA(J9:M9)>0,OR(J9="",K9="",L9="",M9="")),"Completa los 4 campos de moneda extranjera. ","")&IF(AND(J9<>"",COUNTIF(Catalogos!$F$6,J9)=0),"Moneda de factura inválida. ","")&IF(AND(K9<>"",K9<=0),"Monto de factura inválido. ","")&IF(AND(L9<>"",L9<=0),"Tipo de cambio inválido. ","")))
A10: =IF(COUNTA(B10:N10)=0,"",ROW()-5) | O10: =IF(COUNTA(B10:N10)=0,"",IF(P10="","LISTO","REVISAR")) | P10: =IF(COUNTA(B10:N10)=0,"",TRIM(IF(B10="","Falta categoría. ","")&IF(AND(B10<>"",COUNTIF(Catalogos!$B$6:$B$12,B10)=0),"Categoría inválida. ","")&IF(C10="","Falta centro de costo. ","")&IF(D10="","Falta partida. ","")&IF(E10="","Falta fecha. ","")&IF(F10="","Falta concepto. ","")&IF(G10="","Falta proveedor. ","")&IF(I10="","Falta monto. ","")&IF(AND(I10<>"",I10<=0),"Monto inválido. ","")&IF(AND(COUNTA(J10:M10)>0,OR(J10="",K10="",L10="",M10="")),"Completa los 4 campos de moneda extranjera. ","")&IF(AND(J10<>"",COUNTIF(Catalogos!$F$6:$F$6,J10)=0),"Moneda de factura inválida. ","")&IF(AND(K10<>"",K10<=0),"Monto de factura inválido. ","")&IF(AND(L10<>"",L10<=0),"Tipo de cambio inválido. ","")))
A11: =IF(COUNTA(B11:N11)=0,"",ROW()-5) | O11: =IF(COUNTA(B11:N11)=0,"",IF(P11="","LISTO","REVISAR")) | P11: =IF(COUNTA(B11:N11)=0,"",TRIM(IF(B11="","Falta categoría. ","")&IF(AND(B11<>"",COUNTIF(Catalogos!$B$6:$B$12,B11)=0),"Categoría inválida. ","")&IF(C11="","Falta centro de costo. ","")&IF(D11="","Falta partida. ","")&IF(E11="","Falta fecha. ","")&IF(F11="","Falta concepto. ","")&IF(G11="","Falta proveedor. ","")&IF(I11="","Falta monto. ","")&IF(AND(I11<>"",I11<=0),"Monto inválido. ","")&IF(AND(COUNTA(J11:M11)>0,OR(J11="",K11="",L11="",M11="")),"Completa los 4 campos de moneda extranjera. ","")&IF(AND(J11<>"",COUNTIF(Catalogos!$F$6,J11)=0),"Moneda de factura inválida. ","")&IF(AND(K11<>"",K11<=0),"Monto de factura inválido. ","")&IF(AND(L11<>"",L11<=0),"Tipo de cambio inválido. ","")))
A12: =IF(COUNTA(B12:N12)=0,"",ROW()-5) | O12: =IF(COUNTA(B12:N12)=0,"",IF(P12="","LISTO","REVISAR")) | P12: =IF(COUNTA(B12:N12)=0,"",TRIM(IF(B12="","Falta categoría. ","")&IF(AND(B12<>"",COUNTIF(Catalogos!$B$6:$B$12,B12)=0),"Categoría inválida. ","")&IF(C12="","Falta centro de costo. ","")&IF(D12="","Falta partida. ","")&IF(E12="","Falta fecha. ","")&IF(F12="","Falta concepto. ","")&IF(G12="","Falta proveedor. ","")&IF(I12="","Falta monto. ","")&IF(AND(I12<>"",I12<=0),"Monto inválido. ","")&IF(AND(COUNTA(J12:M12)>0,OR(J12="",K12="",L12="",M12="")),"Completa los 4 campos de moneda extranjera. ","")&IF(AND(J12<>"",COUNTIF(Catalogos!$F$6,J12)=0),"Moneda de factura inválida. ","")&IF(AND(K12<>"",K12<=0),"Monto de factura inválido. ","")&IF(AND(L12<>"",L12<=0),"Tipo de cambio inválido. ","")))
A13: =IF(COUNTA(B13:N13)=0,"",ROW()-5) | O13: =IF(COUNTA(B13:N13)=0,"",IF(P13="","LISTO","REVISAR")) | P13: =IF(COUNTA(B13:N13)=0,"",TRIM(IF(B13="","Falta categoría. ","")&IF(AND(B13<>"",COUNTIF(Catalogos!$B$6:$B$12,B13)=0),"Categoría inválida. ","")&IF(C13="","Falta centro de costo. ","")&IF(D13="","Falta partida. ","")&IF(E13="","Falta fecha. ","")&IF(F13="","Falta concepto. ","")&IF(G13="","Falta proveedor. ","")&IF(I13="","Falta monto. ","")&IF(AND(I13<>"",I13<=0),"Monto inválido. ","")&IF(AND(COUNTA(J13:M13)>0,OR(J13="",K13="",L13="",M13="")),"Completa los 4 campos de moneda extranjera. ","")&IF(AND(J13<>"",COUNTIF(Catalogos!$F$6,J13)=0),"Moneda de factura inválida. ","")&IF(AND(K13<>"",K13<=0),"Monto de factura inválido. ","")&IF(AND(L13<>"",L13<=0),"Tipo de cambio inválido. ","")))
A14: =IF(COUNTA(B14:N14)=0,"",ROW()-5) | O14: =IF(COUNTA(B14:N14)=0,"",IF(P14="","LISTO","REVISAR")) | P14: =IF(COUNTA(B14:N14)=0,"",TRIM(IF(B14="","Falta categoría. ","")&IF(AND(B14<>"",COUNTIF(Catalogos!$B$6:$B$12,B14)=0),"Categoría inválida. ","")&IF(C14="","Falta centro de costo. ","")&IF(D14="","Falta partida. ","")&IF(E14="","Falta fecha. ","")&IF(F14="","Falta concepto. ","")&IF(G14="","Falta proveedor. ","")&IF(I14="","Falta monto. ","")&IF(AND(I14<>"",I14<=0),"Monto inválido. ","")&IF(AND(COUNTA(J14:M14)>0,OR(J14="",K14="",L14="",M14="")),"Completa los 4 campos de moneda extranjera. ","")&IF(AND(J14<>"",COUNTIF(Catalogos!$F$6,J14)=0),"Moneda de factura inválida. ","")&IF(AND(K14<>"",K14<=0),"Monto de factura inválido. ","")&IF(AND(L14<>"",L14<=0),"Tipo de cambio inválido. ","")))
A15: =IF(COUNTA(B15:N15)=0,"",ROW()-5) | O15: =IF(COUNTA(B15:N15)=0,"",IF(P15="","LISTO","REVISAR")) | P15: =IF(COUNTA(B15:N15)=0,"",TRIM(IF(B15="","Falta categoría. ","")&IF(AND(B15<>"",COUNTIF(Catalogos!$B$6:$B$12,B15)=0),"Categoría inválida. ","")&IF(C15="","Falta centro de costo. ","")&IF(D15="","Falta partida. ","")&IF(E15="","Falta fecha. ","")&IF(F15="","Falta concepto. ","")&IF(G15="","Falta proveedor. ","")&IF(I15="","Falta monto. ","")&IF(AND(I15<>"",I15<=0),"Monto inválido. ","")&IF(AND(COUNTA(J15:M15)>0,OR(J15="",K15="",L15="",M15="")),"Completa los 4 campos de moneda extranjera. ","")&IF(AND(J15<>"",COUNTIF(Catalogos!$F$6,J15)=0),"Moneda de factura inválida. ","")&IF(AND(K15<>"",K15<=0),"Monto de factura inválido. ","")&IF(AND(L15<>"",L15<=0),"Tipo de cambio inválido. ","")))
A16: =IF(COUNTA(B16:N16)=0,"",ROW()-5) | O16: =IF(COUNTA(B16:N16)=0,"",IF(P16="","LISTO","REVISAR")) | P16: =IF(COUNTA(B16:N16)=0,"",TRIM(IF(B16="","Falta categoría. ","")&IF(AND(B16<>"",COUNTIF(Catalogos!$B$6:$B$12,B16)=0),"Categoría inválida. ","")&IF(C16="","Falta centro de costo. ","")&IF(D16="","Falta partida. ","")&IF(E16="","Falta fecha. ","")&IF(F16="","Falta concepto. ","")&IF(G16="","Falta proveedor. ","")&IF(I16="","Falta monto. ","")&IF(AND(I16<>"",I16<=0),"Monto inválido. ","")&IF(AND(COUNTA(J16:M16)>0,OR(J16="",K16="",L16="",M16="")),"Completa los 4 campos de moneda extranjera. ","")&IF(AND(J16<>"",COUNTIF(Catalogos!$F$6,J16)=0),"Moneda de factura inválida. ","")&IF(AND(K16<>"",K16<=0),"Monto de factura inválido. ","")&IF(AND(L16<>"",L16<=0),"Tipo de cambio inválido. ","")))
A17: =IF(COUNTA(B17:N17)=0,"",ROW()-5) | O17: =IF(COUNTA(B17:N17)=0,"",IF(P17="","LISTO","REVISAR")) | P17: =IF(COUNTA(B17:N17)=0,"",TRIM(IF(B17="","Falta categoría. ","")&IF(AND(B17<>"",COUNTIF(Catalogos!$B$6:$B$12,B17)=0),"Categoría inválida. ","")&IF(C17="","Falta centro de costo. ","")&IF(D17="","Falta partida. ","")&IF(E17="","Falta fecha. ","")&IF(F17="","Falta concepto. ","")&IF(G17="","Falta proveedor. ","")&IF(I17="","Falta monto. ","")&IF(AND(I17<>"",I17<=0),"Monto inválido. ","")&IF(AND(COUNTA(J17:M17)>0,OR(J17="",K17="",L17="",M17="")),"Completa los 4 campos de moneda extranjera. ","")&IF(AND(J17<>"",COUNTIF(Catalogos!$F$6,J17)=0),"Moneda de factura inválida. ","")&IF(AND(K17<>"",K17<=0),"Monto de factura inválido. ","")&IF(AND(L17<>"",L17<=0),"Tipo de cambio inválido. ","")))
A18: =IF(COUNTA(B18:N18)=0,"",ROW()-5) | O18: =IF(COUNTA(B18:N18)=0,"",IF(P18="","LISTO","REVISAR")) | P18: =IF(COUNTA(B18:N18)=0,"",TRIM(IF(B18="","Falta categoría. ","")&IF(AND(B18<>"",COUNTIF(Catalogos!$B$6:$B$12,B18)=0),"Categoría inválida. ","")&IF(C18="","Falta centro de costo. ","")&IF(D18="","Falta partida. ","")&IF(E18="","Falta fecha. ","")&IF(F18="","Falta concepto. ","")&IF(G18="","Falta proveedor. ","")&IF(I18="","Falta monto. ","")&IF(AND(I18<>"",I18<=0),"Monto inválido. ","")&IF(AND(COUNTA(J18:M18)>0,OR(J18="",K18="",L18="",M18="")),"Completa los 4 campos de moneda extranjera. ","")&IF(AND(J18<>"",COUNTIF(Catalogos!$F$6,J18)=0),"Moneda de factura inválida. ","")&IF(AND(K18<>"",K18<=0),"Monto de factura inválido. ","")&IF(AND(L18<>"",L18<=0),"Tipo de cambio inválido. ","")))
A19: =IF(COUNTA(B19:N19)=0,"",ROW()-5) | O19: =IF(COUNTA(B19:N19)=0,"",IF(P19="","LISTO","REVISAR")) | P19: =IF(COUNTA(B19:N19)=0,"",TRIM(IF(B19="","Falta categoría. ","")&IF(AND(B19<>"",COUNTIF(Catalogos!$B$6:$B$12,B19)=0),"Categoría inválida. ","")&IF(C19="","Falta centro de costo. ","")&IF(D19="","Falta partida. ","")&IF(E19="","Falta fecha. ","")&IF(F19="","Falta concepto. ","")&IF(G19="","Falta proveedor. ","")&IF(I19="","Falta monto. ","")&IF(AND(I19<>"",I19<=0),"Monto inválido. ","")&IF(AND(COUNTA(J19:M19)>0,OR(J19="",K19="",L19="",M19="")),"Completa los 4 campos de moneda extranjera. ","")&IF(AND(J19<>"",COUNTIF(Catalogos!$F$6,J19)=0),"Moneda de factura inválida. ","")&IF(AND(K19<>"",K19<=0),"Monto de factura inválido. ","")&IF(AND(L19<>"",L19<=0),"Tipo de cambio inválido. ","")))
A20: =IF(COUNTA(B20:N20)=0,"",ROW()-5) | O20: =IF(COUNTA(B20:N20)=0,"",IF(P20="","LISTO","REVISAR")) | P20: =IF(COUNTA(B20:N20)=0,"",TRIM(IF(B20="","Falta categoría. ","")&IF(AND(B20<>"",COUNTIF(Catalogos!$B$6:$B$12,B20)=0),"Categoría inválida. ","")&IF(C20="","Falta centro de costo. ","")&IF(D20="","Falta partida. ","")&IF(E20="","Falta fecha. ","")&IF(F20="","Falta concepto. ","")&IF(G20="","Falta proveedor. ","")&IF(I20="","Falta monto. ","")&IF(AND(I20<>"",I20<=0),"Monto inválido. ","")&IF(AND(COUNTA(J20:M20)>0,OR(J20="",K20="",L20="",M20="")),"Completa los 4 campos de moneda extranjera. ","")&IF(AND(J20<>"",COUNTIF(Catalogos!$F$6,J20)=0),"Moneda de factura inválida. ","")&IF(AND(K20<>"",K20<=0),"Monto de factura inválido. ","")&IF(AND(L20<>"",L20<=0),"Tipo de cambio inválido. ","")))
A21: =IF(COUNTA(B21:N21)=0,"",ROW()-5) | O21: =IF(COUNTA(B21:N21)=0,"",IF(P21="","LISTO","REVISAR")) | P21: =IF(COUNTA(B21:N21)=0,"",TRIM(IF(B21="","Falta categoría. ","")&IF(AND(B21<>"",COUNTIF(Catalogos!$B$6:$B$12,B21)=0),"Categoría inválida. ","")&IF(C21="","Falta centro de costo. ","")&IF(D21="","Falta partida. ","")&IF(E21="","Falta fecha. ","")&IF(F21="","Falta concepto. ","")&IF(G21="","Falta proveedor. ","")&IF(I21="","Falta monto. ","")&IF(AND(I21<>"",I21<=0),"Monto inválido. ","")&IF(AND(COUNTA(J21:M21)>0,OR(J21="",K21="",L21="",M21="")),"Completa los 4 campos de moneda extranjera. ","")&IF(AND(J21<>"",COUNTIF(Catalogos!$F$6,J21)=0),"Moneda de factura inválida. ","")&IF(AND(K21<>"",K21<=0),"Monto de factura inválido. ","")&IF(AND(L21<>"",L21<=0),"Tipo de cambio inválido. ","")))
A22: =IF(COUNTA(B22:N22)=0,"",ROW()-5) | O22: =IF(COUNTA(B22:N22)=0,"",IF(P22="","LISTO","REVISAR")) | P22: =IF(COUNTA(B22:N22)=0,"",TRIM(IF(B22="","Falta categoría. ","")&IF(AND(B22<>"",COUNTIF(Catalogos!$B$6:$B$12,B22)=0),"Categoría inválida. ","")&IF(C22="","Falta centro de costo. ","")&IF(D22="","Falta partida. ","")&IF(E22="","Falta fecha. ","")&IF(F22="","Falta concepto. ","")&IF(G22="","Falta proveedor. ","")&IF(I22="","Falta monto. ","")&IF(AND(I22<>"",I22<=0),"Monto inválido. ","")&IF(AND(COUNTA(J22:M22)>0,OR(J22="",K22="",L22="",M22="")),"Completa los 4 campos de moneda extranjera. ","")&IF(AND(J22<>"",COUNTIF(Catalogos!$F$6,J22)=0),"Moneda de factura inválida. ","")&IF(AND(K22<>"",K22<=0),"Monto de factura inválido. ","")&IF(AND(L22<>"",L22<=0),"Tipo de cambio inválido. ","")))
... A99: =IF(COUNTA(B99:N99)=0,"",ROW()-5) | O99: =IF(COUNTA(B99:N99)=0,"",IF(P99="","LISTO","REVISAR")) | P99: =IF(COUNTA(B99:N99)=0,"",TRIM(IF(B99="","Falta categoría. ","")&IF(AND(B99<>"",COUNTIF(Catalogos!$B$6:$B$12,B99)=0),"Categoría inválida. ","")&IF(C99="","Falta centro de costo. ","")&IF(D99="","Falta partida. ","")&IF(E99="","Falta fecha. ","")&IF(F99="","Falta concepto. ","")&IF(G99="","Falta proveedor. ","")&IF(I99="","Falta monto. ","")&IF(AND(I99<>"",I99<=0),"Monto inválido. ","")&IF(AND(COUNTA(J99:M99)>0,OR(J99="",K99="",L99="",M99="")),"Completa los 4 campos de moneda extranjera. ","")&IF(AND(J99<>"",COUNTIF(Catalogos!$F$6,J99)=0),"Moneda de factura inválida. ","")&IF(AND(K99<>"",K99<=0),"Monto de factura inválido. ","")&IF(AND(L99<>"",L99<=0),"Tipo de cambio inválido. ","")))
A100: =IF(COUNTA(B100:N100)=0,"",ROW()-5) | O100: =IF(COUNTA(B100:N100)=0,"",IF(P100="","LISTO","REVISAR")) | P100: =IF(COUNTA(B100:N100)=0,"",TRIM(IF(B100="","Falta categoría. ","")&IF(AND(B100<>"",COUNTIF(Catalogos!$B$6:$B$12,B100)=0),"Categoría inválida. ","")&IF(C100="","Falta centro de costo. ","")&IF(D100="","Falta partida. ","")&IF(E100="","Falta fecha. ","")&IF(F100="","Falta concepto. ","")&IF(G100="","Falta proveedor. ","")&IF(I100="","Falta monto. ","")&IF(AND(I100<>"",I100<=0),"Monto inválido. ","")&IF(AND(COUNTA(J100:M100)>0,OR(J100="",K100="",L100="",M100="")),"Completa los 4 campos de moneda extranjera. ","")&IF(AND(J100<>"",COUNTIF(Catalogos!$F$6:$F$6,J100)=0),"Moneda de factura inválida. ","")&IF(AND(K100<>"",K100<=0),"Monto de factura inválido. ","")&IF(AND(L100<>"",L100<=0),"Tipo de cambio inválido. ","")))
A101: =IF(COUNTA(B101:N101)=0,"",ROW()-5) | O101: =IF(COUNTA(B101:N101)=0,"",IF(P101="","LISTO","REVISAR")) | P101: =IF(COUNTA(B101:N101)=0,"",TRIM(IF(B101="","Falta categoría. ","")&IF(AND(B101<>"",COUNTIF(Catalogos!$B$6:$B$12,B101)=0),"Categoría inválida. ","")&IF(C101="","Falta centro de costo. ","")&IF(D101="","Falta partida. ","")&IF(E101="","Falta fecha. ","")&IF(F101="","Falta concepto. ","")&IF(G101="","Falta proveedor. ","")&IF(I101="","Falta monto. ","")&IF(AND(I101<>"",I101<=0),"Monto inválido. ","")&IF(AND(COUNTA(J101:M101)>0,OR(J101="",K101="",L101="",M101="")),"Completa los 4 campos de moneda extranjera. ","")&IF(AND(J101<>"",COUNTIF(Catalogos!$F$6,J101)=0),"Moneda de factura inválida. ","")&IF(AND(K101<>"",K101<=0),"Monto de factura inválido. ","")&IF(AND(L101<>"",L101<=0),"Tipo de cambio inválido. ","")))
A102: =IF(COUNTA(B102:N102)=0,"",ROW()-5) | O102: =IF(COUNTA(B102:N102)=0,"",IF(P102="","LISTO","REVISAR")) | P102: =IF(COUNTA(B102:N102)=0,"",TRIM(IF(B102="","Falta categoría. ","")&IF(AND(B102<>"",COUNTIF(Catalogos!$B$6:$B$12,B102)=0),"Categoría inválida. ","")&IF(C102="","Falta centro de costo. ","")&IF(D102="","Falta partida. ","")&IF(E102="","Falta fecha. ","")&IF(F102="","Falta concepto. ","")&IF(G102="","Falta proveedor. ","")&IF(I102="","Falta monto. ","")&IF(AND(I102<>"",I102<=0),"Monto inválido. ","")&IF(AND(COUNTA(J102:M102)>0,OR(J102="",K102="",L102="",M102="")),"Completa los 4 campos de moneda extranjera. ","")&IF(AND(J102<>"",COUNTIF(Catalogos!$F$6,J102)=0),"Moneda de factura inválida. ","")&IF(AND(K102<>"",K102<=0),"Monto de factura inválido. ","")&IF(AND(L102<>"",L102<=0),"Tipo de cambio inválido. ","")))
A103: =IF(COUNTA(B103:N103)=0,"",ROW()-5) | O103: =IF(COUNTA(B103:N103)=0,"",IF(P103="","LISTO","REVISAR")) | P103: =IF(COUNTA(B103:N103)=0,"",TRIM(IF(B103="","Falta categoría. ","")&IF(AND(B103<>"",COUNTIF(Catalogos!$B$6:$B$12,B103)=0),"Categoría inválida. ","")&IF(C103="","Falta centro de costo. ","")&IF(D103="","Falta partida. ","")&IF(E103="","Falta fecha. ","")&IF(F103="","Falta concepto. ","")&IF(G103="","Falta proveedor. ","")&IF(I103="","Falta monto. ","")&IF(AND(I103<>"",I103<=0),"Monto inválido. ","")&IF(AND(COUNTA(J103:M103)>0,OR(J103="",K103="",L103="",M103="")),"Completa los 4 campos de moneda extranjera. ","")&IF(AND(J103<>"",COUNTIF(Catalogos!$F$6,J103)=0),"Moneda de factura inválida. ","")&IF(AND(K103<>"",K103<=0),"Monto de factura inválido. ","")&IF(AND(L103<>"",L103<=0),"Tipo de cambio inválido. ","")))
A104: =IF(COUNTA(B104:N104)=0,"",ROW()-5) | O104: =IF(COUNTA(B104:N104)=0,"",IF(P104="","LISTO","REVISAR")) | P104: =IF(COUNTA(B104:N104)=0,"",TRIM(IF(B104="","Falta categoría. ","")&IF(AND(B104<>"",COUNTIF(Catalogos!$B$6:$B$12,B104)=0),"Categoría inválida. ","")&IF(C104="","Falta centro de costo. ","")&IF(D104="","Falta partida. ","")&IF(E104="","Falta fecha. ","")&IF(F104="","Falta concepto. ","")&IF(G104="","Falta proveedor. ","")&IF(I104="","Falta monto. ","")&IF(AND(I104<>"",I104<=0),"Monto inválido. ","")&IF(AND(COUNTA(J104:M104)>0,OR(J104="",K104="",L104="",M104="")),"Completa los 4 campos de moneda extranjera. ","")&IF(AND(J104<>"",COUNTIF(Catalogos!$F$6,J104)=0),"Moneda de factura inválida. ","")&IF(AND(K104<>"",K104<=0),"Monto de factura inválido. ","")&IF(AND(L104<>"",L104<=0),"Tipo de cambio inválido. ","")))
A105: =IF(COUNTA(B105:N105)=0,"",ROW()-5) | O105: =IF(COUNTA(B105:N105)=0,"",IF(P105="","LISTO","REVISAR")) | P105: =IF(COUNTA(B105:N105)=0,"",TRIM(IF(B105="","Falta categoría. ","")&IF(AND(B105<>"",COUNTIF(Catalogos!$B$6:$B$12,B105)=0),"Categoría inválida. ","")&IF(C105="","Falta centro de costo. ","")&IF(D105="","Falta partida. ","")&IF(E105="","Falta fecha. ","")&IF(F105="","Falta concepto. ","")&IF(G105="","Falta proveedor. ","")&IF(I105="","Falta monto. ","")&IF(AND(I105<>"",I105<=0),"Monto inválido. ","")&IF(AND(COUNTA(J105:M105)>0,OR(J105="",K105="",L105="",M105="")),"Completa los 4 campos de moneda extranjera. ","")&IF(AND(J105<>"",COUNTIF(Catalogos!$F$6,J105)=0),"Moneda de factura inválida. ","")&IF(AND(K105<>"",K105<=0),"Monto de factura inválido. ","")&IF(AND(L105<>"",L105<=0),"Tipo de cambio inválido. ","")))
A106: =IF(COUNTA(B106:N106)=0,"",ROW()-5) | O106: =IF(COUNTA(B106:N106)=0,"",IF(P106="","LISTO","REVISAR")) | P106: =IF(COUNTA(B106:N106)=0,"",TRIM(IF(B106="","Falta categoría. ","")&IF(AND(B106<>"",COUNTIF(Catalogos!$B$6:$B$12,B106)=0),"Categoría inválida. ","")&IF(C106="","Falta centro de costo. ","")&IF(D106="","Falta partida. ","")&IF(E106="","Falta fecha. ","")&IF(F106="","Falta concepto. ","")&IF(G106="","Falta proveedor. ","")&IF(I106="","Falta monto. ","")&IF(AND(I106<>"",I106<=0),"Monto inválido. ","")&IF(AND(COUNTA(J106:M106)>0,OR(J106="",K106="",L106="",M106="")),"Completa los 4 campos de moneda extranjera. ","")&IF(AND(J106<>"",COUNTIF(Catalogos!$F$6,J106)=0),"Moneda de factura inválida. ","")&IF(AND(K106<>"",K106<=0),"Monto de factura inválido. ","")&IF(AND(L106<>"",L106<=0),"Tipo de cambio inválido. ","")))
A107: =IF(COUNTA(B107:N107)=0,"",ROW()-5) | O107: =IF(COUNTA(B107:N107)=0,"",IF(P107="","LISTO","REVISAR")) | P107: =IF(COUNTA(B107:N107)=0,"",TRIM(IF(B107="","Falta categoría. ","")&IF(AND(B107<>"",COUNTIF(Catalogos!$B$6:$B$12,B107)=0),"Categoría inválida. ","")&IF(C107="","Falta centro de costo. ","")&IF(D107="","Falta partida. ","")&IF(E107="","Falta fecha. ","")&IF(F107="","Falta concepto. ","")&IF(G107="","Falta proveedor. ","")&IF(I107="","Falta monto. ","")&IF(AND(I107<>"",I107<=0),"Monto inválido. ","")&IF(AND(COUNTA(J107:M107)>0,OR(J107="",K107="",L107="",M107="")),"Completa los 4 campos de moneda extranjera. ","")&IF(AND(J107<>"",COUNTIF(Catalogos!$F$6,J107)=0),"Moneda de factura inválida. ","")&IF(AND(K107<>"",K107<=0),"Monto de factura inválido. ","")&IF(AND(L107<>"",L107<=0),"Tipo de cambio inválido. ","")))
A108: =IF(COUNTA(B108:N108)=0,"",ROW()-5) | O108: =IF(COUNTA(B108:N108)=0,"",IF(P108="","LISTO","REVISAR")) | P108: =IF(COUNTA(B108:N108)=0,"",TRIM(IF(B108="","Falta categoría. ","")&IF(AND(B108<>"",COUNTIF(Catalogos!$B$6:$B$12,B108)=0),"Categoría inválida. ","")&IF(C108="","Falta centro de costo. ","")&IF(D108="","Falta partida. ","")&IF(E108="","Falta fecha. ","")&IF(F108="","Falta concepto. ","")&IF(G108="","Falta proveedor. ","")&IF(I108="","Falta monto. ","")&IF(AND(I108<>"",I108<=0),"Monto inválido. ","")&IF(AND(COUNTA(J108:M108)>0,OR(J108="",K108="",L108="",M108="")),"Completa los 4 campos de moneda extranjera. ","")&IF(AND(J108<>"",COUNTIF(Catalogos!$F$6,J108)=0),"Moneda de factura inválida. ","")&IF(AND(K108<>"",K108<=0),"Monto de factura inválido. ","")&IF(AND(L108<>"",L108<=0),"Tipo de cambio inválido. ","")))
A109: =IF(COUNTA(B109:N109)=0,"",ROW()-5) | O109: =IF(COUNTA(B109:N109)=0,"",IF(P109="","LISTO","REVISAR")) | P109: =IF(COUNTA(B109:N109)=0,"",TRIM(IF(B109="","Falta categoría. ","")&IF(AND(B109<>"",COUNTIF(Catalogos!$B$6:$B$12,B109)=0),"Categoría inválida. ","")&IF(C109="","Falta centro de costo. ","")&IF(D109="","Falta partida. ","")&IF(E109="","Falta fecha. ","")&IF(F109="","Falta concepto. ","")&IF(G109="","Falta proveedor. ","")&IF(I109="","Falta monto. ","")&IF(AND(I109<>"",I109<=0),"Monto inválido. ","")&IF(AND(COUNTA(J109:M109)>0,OR(J109="",K109="",L109="",M109="")),"Completa los 4 campos de moneda extranjera. ","")&IF(AND(J109<>"",COUNTIF(Catalogos!$F$6,J109)=0),"Moneda de factura inválida. ","")&IF(AND(K109<>"",K109<=0),"Monto de factura inválido. ","")&IF(AND(L109<>"",L109<=0),"Tipo de cambio inválido. ","")))
A110: =IF(COUNTA(B110:N110)=0,"",ROW()-5) | O110: =IF(COUNTA(B110:N110)=0,"",IF(P110="","LISTO","REVISAR")) | P110: =IF(COUNTA(B110:N110)=0,"",TRIM(IF(B110="","Falta categoría. ","")&IF(AND(B110<>"",COUNTIF(Catalogos!$B$6:$B$12,B110)=0),"Categoría inválida. ","")&IF(C110="","Falta centro de costo. ","")&IF(D110="","Falta partida. ","")&IF(E110="","Falta fecha. ","")&IF(F110="","Falta concepto. ","")&IF(G110="","Falta proveedor. ","")&IF(I110="","Falta monto. ","")&IF(AND(I110<>"",I110<=0),"Monto inválido. ","")&IF(AND(COUNTA(J110:M110)>0,OR(J110="",K110="",L110="",M110="")),"Completa los 4 campos de moneda extranjera. ","")&IF(AND(J110<>"",COUNTIF(Catalogos!$F$6,J110)=0),"Moneda de factura inválida. ","")&IF(AND(K110<>"",K110<=0),"Monto de factura inválido. ","")&IF(AND(L110<>"",L110<=0),"Tipo de cambio inválido. ","")))
A111: =IF(COUNTA(B111:N111)=0,"",ROW()-5) | O111: =IF(COUNTA(B111:N111)=0,"",IF(P111="","LISTO","REVISAR")) | P111: =IF(COUNTA(B111:N111)=0,"",TRIM(IF(B111="","Falta categoría. ","")&IF(AND(B111<>"",COUNTIF(Catalogos!$B$6:$B$12,B111)=0),"Categoría inválida. ","")&IF(C111="","Falta centro de costo. ","")&IF(D111="","Falta partida. ","")&IF(E111="","Falta fecha. ","")&IF(F111="","Falta concepto. ","")&IF(G111="","Falta proveedor. ","")&IF(I111="","Falta monto. ","")&IF(AND(I111<>"",I111<=0),"Monto inválido. ","")&IF(AND(COUNTA(J111:M111)>0,OR(J111="",K111="",L111="",M111="")),"Completa los 4 campos de moneda extranjera. ","")&IF(AND(J111<>"",COUNTIF(Catalogos!$F$6,J111)=0),"Moneda de factura inválida. ","")&IF(AND(K111<>"",K111<=0),"Monto de factura inválido. ","")&IF(AND(L111<>"",L111<=0),"Tipo de cambio inválido. ","")))
A112: =IF(COUNTA(B112:N112)=0,"",ROW()-5) | O112: =IF(COUNTA(B112:N112)=0,"",IF(P112="","LISTO","REVISAR")) | P112: =IF(COUNTA(B112:N112)=0,"",TRIM(IF(B112="","Falta categoría. ","")&IF(AND(B112<>"",COUNTIF(Catalogos!$B$6:$B$12,B112)=0),"Categoría inválida. ","")&IF(C112="","Falta centro de costo. ","")&IF(D112="","Falta partida. ","")&IF(E112="","Falta fecha. ","")&IF(F112="","Falta concepto. ","")&IF(G112="","Falta proveedor. ","")&IF(I112="","Falta monto. ","")&IF(AND(I112<>"",I112<=0),"Monto inválido. ","")&IF(AND(COUNTA(J112:M112)>0,OR(J112="",K112="",L112="",M112="")),"Completa los 4 campos de moneda extranjera. ","")&IF(AND(J112<>"",COUNTIF(Catalogos!$F$6,J112)=0),"Moneda de factura inválida. ","")&IF(AND(K112<>"",K112<=0),"Monto de factura inválido. ","")&IF(AND(L112<>"",L112<=0),"Tipo de cambio inválido. ","")))
... A205: =IF(COUNTA(B205:N205)=0,"",ROW()-5) | O205: =IF(COUNTA(B205:N205)=0,"",IF(P205="","LISTO","REVISAR")) | P205: =IF(COUNTA(B205:N205)=0,"",TRIM(IF(B205="","Falta categoría. ","")&IF(AND(B205<>"",COUNTIF(Catalogos!$B$6:$B$12,B205)=0),"Categoría inválida. ","")&IF(C205="","Falta centro de costo. ","")&IF(D205="","Falta partida. ","")&IF(E205="","Falta fecha. ","")&IF(F205="","Falta concepto. ","")&IF(G205="","Falta proveedor. ","")&IF(I205="","Falta monto. ","")&IF(AND(I205<>"",I205<=0),"Monto inválido. ","")&IF(AND(COUNTA(J205:M205)>0,OR(J205="",K205="",L205="",M205="")),"Completa los 4 campos de moneda extranjera. ","")&IF(AND(J205<>"",COUNTIF(Catalogos!$F$6,J205)=0),"Moneda de factura inválida. ","")&IF(AND(K205<>"",K205<=0),"Monto de factura inválido. ","")&IF(AND(L205<>"",L205<=0),"Tipo de cambio inválido. ","")))

Sheet Instrucciones
A2: Cómo usar la plantilla
A3: La hoja de carga usa los campos funcionales del ERP y deja los identificadores técnicos al proceso de importación.
A5: Pasos
A6: 1 | B6: Seleccione el código de categoría.
A7: 2 | B7: Escriba centro de costo, partida y proveedor tal como aparecen en el ERP.
A8: 3 | B8: Complete fecha, concepto, descripción y monto contable.
A9: 4 | B9: Si la factura está en dólares, complete los cuatro campos de moneda extranjera.
A10: 5 | B10: Importe solo las filas cuyo Estado de fila sea LISTO.
A12: Reglas de carga
A13: Regla | B13: Detalle
A14: Una fila por gasto | B14: No agrupe varios gastos en una sola fila.
A15: Fechas | B15: Use fechas reales de Excel; el formato visible es dd/mm/aaaa.
A16: Monto | B16: Debe ser mayor que cero y corresponder al monto contable que guardará el ERP.
A17: Moneda extranjera | B17: Moneda factura, monto factura, tipo de cambio y fecha TC se completan juntos.
A18: Campos opcionales | B18: Descripción y Factura(s) pueden quedar en blanco.
A19: Estructura | B19: No cambie nombres, orden ni cantidad de columnas en Carga masiva.
A21: Correspondencia con contable.GastoDirecto
A22: Campo de base de datos | B22: Origen | C22: Tratamiento | D22: Se escribe en Excel
A23: IdGastoDirecto | B23: Sistema | C23: Se genera al insertar | D23: No
A24: IdPresupuestoDetalle | B24: Centro de costo + Partida | C24: El importador resuelve la FK | D24: Indirecto
A25: IdProveedor | B25: Proveedor | C25: El importador resuelve la FK | D25: Indirecto
A26: IdMoneda | B26: Configuración del gasto | C26: El importador resuelve la FK | D26: No directo
A27: Fecha | B27: Fecha | C27: Carga directa | D27: Sí
A28: Concepto | B28: Concepto | C28: Carga directa | D28: Sí
A29: Descripcion | B29: Descripción | C29: Carga directa | D29: Sí, opcional
A30: Monto | B30: Monto | C30: Carga directa | D30: Sí
A31: Estado / auditoría | B31: Sistema | C31: Estado y fechas se generan en el ERP | D31: No
A32: IdMonedaOriginal / MontoOriginal | B32: Moneda factura / Monto factura | C32: Se usan solo para moneda extranjera | D32: Condicional
A33: TipoCambio / FechaTipoCambio | B33: Tipo de cambio / Fecha tipo cambio | C33: Carga directa si hay moneda extranjera | D33: Condicional
A34: IdCategoriaGasto | B34: Categoría código | C34: Se resuelve usando Catalogos | D34: Indirecto
A36: Alcance pendiente de definir en el importador
A37: Proveedores | B37: Definir si se buscarán por nombre, RUC/documento o código interno.
A38: Centros y partidas | B38: Definir el identificador único y validar que la partida pertenezca al centro de costo.
A39: Factura(s) | B39: La tabla GastoDirecto no contiene este dato; el importador debe gestionar la relación correspondiente.

Sheet Ejemplos
A2: Ejemplos de llenado
A3: Estos registros son ilustrativos. No copie los datos sin reemplazarlos por información real.
A5: Categoría código | B5: Centro de costo | C5: Partida | D5: Fecha | E5: Concepto | F5: Proveedor | G5: Descripción | H5: Monto | I5: Moneda factura | J5: Monto factura | K5: Tipo de cambio | L5: Fecha tipo cambio | M5: Factura(s) | N5: Resultado esperado
A6: ADMINISTRATIVO | B6: Administración general | C6: Servicios profesionales | D6: 46296.5 | E6: Honorarios contables - octubre | F6: Estudio Contable ABC | G6: Servicio mensual de contabilidad | H6: 2500 | M6: F001-245 | N6: LISTO
A7: MARKETING_VENTAS | B7: Proyecto Talara 702 | C7: Publicidad digital | D7: 46300.5 | E7: Campaña digital - octubre | F7: Proveedor de publicidad | G7: Factura emitida en dólares | H7: 1880 | I7: USD | J7: 500 | K7: 3.76 | L7: 46300.5 | M7: INV-10025 | N7: LISTO
A8: TERRENO | B8: Proyecto Mayta Cápac 1248 | C8: Estudios preliminares | D8: 46303.5 | E8: Levantamiento topográfico | F8: Topografía SAC | G8: Servicio para evaluación del terreno | H8: 3200 | N8: LISTO

Sheet Catalogos
A2: Catálogos para la carga masiva
A3: Estos códigos son los que debe usar la hoja Carga masiva.
A5: Id categoría | B5: Código | C5: Nombre | D5: Módulo del ERP | F5: Código moneda | G5: Uso
A6: 26 | B6: OTROS | C6: OTROS GASTOS | D6: Otros Gastos | F6: USD | G6: Factura emitida en dólares
A7: 27 | B7: MARKETING_VENTAS | C7: MARKETING Y VENTAS | D7: Marketing / Ventas
A8: 28 | B8: TERRENO | C8: TERRENO | D8: Terreno - Anteproyecto - Proyecto | F8: Referencias que faltan incorporar
A9: 29 | B9: ANTEPROYECTO | C9: ANTEPROYECTO | D9: Terreno - Anteproyecto - Proyecto | F9: Catálogo | G9: Identificador recomendado | H9: Uso en la plantilla | I9: Estado | J9: Observación
A10: 30 | B10: PROYECTO | C10: PROYECTO | D10: Terreno - Anteproyecto - Proyecto | F10: Centros de costo | G10: Código único | H10: Centro de costo | I10: Pendiente | J10: Pegar aquí o integrar desde el ERP
A11: 31 | B11: ADMINISTRATIVO | C11: GASTOS ADMINISTRATIVOS | D11: Gastos administrativos | F11: Partidas | G11: Código único | H11: Partida | I11: Pendiente | J11: Debe corresponder al centro de costo
A12: 32 | B12: MUNICIPAL | C12: GASTOS MUNICIPALES | D12: Gastos municipales y distritales | F12: Proveedores | G12: RUC / documento | H12: Proveedor | I12: Pendiente | J12: Evita ambigüedad por nombres repetidos
